giants/__init__.py
giants/__version__.py
giants/config.py
giants/model.py
giants/test/__init__.py
giants/test/test_model.py
giants-1.0.0.dist-info/LICENSE
giants-1.0.0.dist-info/METADATA
giants-1.0.0.dist-info/WHEEL
giants-1.0.0.dist-info/top_level.txt
giants-1.0.0.dist-info/RECORD
