Metadata-Version: 2.1
Name: giants
Version: 1.0.0
Summary: Statistical and geospatial modeling tools for mapping big trees.
Home-page: https://the.forestobservatory.com/giants
Author: Salo Sciences
Author-email: cba@salo.ai
License: MIT
Keywords: ecology,conservation,remote sensing,machine learning
Platform: any
Classifier: Programming Language :: Python :: 3
Classifier: License :: OSI Approved :: MIT License
Classifier: Operating System :: OS Independent
Requires-Python: >=3.0
Requires-Dist: numpy (>=1.21.2)
Requires-Dist: scikit-learn (>=0.24.2)
